previz/__init__.py
previz-1.0.1.dist-info/DESCRIPTION.rst
previz-1.0.1.dist-info/METADATA
previz-1.0.1.dist-info/RECORD
previz-1.0.1.dist-info/WHEEL
previz-1.0.1.dist-info/metadata.json
previz-1.0.1.dist-info/top_level.txt
