Metadata-Version: 2.0
Name: previz
Version: 1.0.1
Summary: Previz REST API python wrapper
Home-page: https://github.com/Previz-app/previz-python-api
Author: Previz
Author-email: info@previz.co
License: MIT
Keywords: previz development 3d scene exporter
Platform: UNKNOWN
Classifier: Development Status :: 3 - Alpha
Classifier: Intended Audience :: Developers
Classifier: Topic :: Multimedia :: Graphics :: 3D Modeling
Classifier: License :: OSI Approved :: MIT License
Classifier: Programming Language :: Python :: 2
Classifier: Programming Language :: Python :: 2.6
Classifier: Programming Language :: Python :: 2.7
Classifier: Programming Language :: Python :: 3
Requires-Dist: requests
Requires-Dist: requests-toolbelt
Requires-Dist: semantic-version
